safisha/__init__.py
safisha/cleaner.py
safisha/cli.py
safisha/utils.py
safisha-0.1.7.dist-info/METADATA
safisha-0.1.7.dist-info/WHEEL
safisha-0.1.7.dist-info/entry_points.txt
safisha-0.1.7.dist-info/top_level.txt
safisha-0.1.7.dist-info/RECORD
